gethyper/__init__.py
gethyper-0.0.1.dist-info/METADATA
gethyper-0.0.1.dist-info/WHEEL
gethyper-0.0.1.dist-info/top_level.txt
gethyper-0.0.1.dist-info/RECORD
