Metadata-Version: 2.1
Name: gethyper
Version: 0.0.1
Summary: A minimal package for reserving the name on PyPI
Home-page: https://github.com/yourgithub/gethyper
Author: Your Name
Author-email: your.email@example.com
License: MIT
Keywords: example package
Platform: UNKNOWN
Classifier: Development Status :: 1 - Planning
Classifier: Intended Audience :: Developers
Classifier: License :: OSI Approved :: MIT License
Classifier: Programming Language :: Python :: 3
Classifier: Programming Language :: Python :: 3.7
Classifier: Programming Language :: Python :: 3.8
Classifier: Programming Language :: Python :: 3.9
Classifier: Programming Language :: Python :: 3.10
